ec2ools/__init__.py
ec2ools/cli.py
ec2ools/cli_asg.py
ec2ools/cli_eip.py
ec2ools/aws/__init__.py
ec2ools/aws/asg.py
ec2ools/aws/ec2.py
ec2ools/aws/eip.py
ec2ools-0.2.5.dist-info/LICENSE
ec2ools-0.2.5.dist-info/METADATA
ec2ools-0.2.5.dist-info/WHEEL
ec2ools-0.2.5.dist-info/entry_points.txt
ec2ools-0.2.5.dist-info/top_level.txt
ec2ools-0.2.5.dist-info/RECORD
