Metadata-Version: 2.1
Name: ec2ools
Version: 0.2.5
Summary: Utilities to manage ec2 instances and asg's
Home-page: https://github.com/ibejohn818/ec2ools
Author: John Hardy
Author-email: john@johnchardy.com
License: MIT license
Keywords: ec2ools
Platform: UNKNOWN
Classifier: Development Status :: 2 - Pre-Alpha
Classifier: Intended Audience :: Developers
Classifier: License :: OSI Approved :: MIT License
Classifier: Natural Language :: English
Classifier: Programming Language :: Python :: 2.7
Classifier: Programming Language :: Python :: 3.7
Classifier: Programming Language :: Python :: 3.8
Requires-Dist: Click (>=7.0)
Requires-Dist: boto3
Requires-Dist: requests
